eventus_integration.py
eventus_integration-1.1.5.dist-info/METADATA
eventus_integration-1.1.5.dist-info/WHEEL
eventus_integration-1.1.5.dist-info/top_level.txt
eventus_integration-1.1.5.dist-info/RECORD
