Metadata-Version: 2.4
Name: eventus-integration
Version: 1.1.5
Summary: A Python library for Eventus integrations: ESDL TCP sender, MongoDB logging, Teams notifications, retry logic, and multi-tenant ingestion.
Author-email: Pratik Thorat <pratik.thorat@eventussecurity.com>
Requires-Python: >=3.8
Requires-Dist: pymongo
Requires-Dist: requests
Requires-Dist: python-dotenv
Requires-Dist: flatten-json
